{
  "post_path": "/home/rene/sage-news/posts/2026-05-04-sage-operations-preislisten-update-mai-2026.md",
  "title": "Preislisten-Update für Sage Operations kommt am 8. Mai 2026",
  "summary": "Sage Operations bekommt am 8. Mai ein Update mit Änderungen an Preislisten, Paketzuordnungen und Bezeichnungen. Wer eigene Reports, Importe, APIs oder Dashboard-Anker nutzt, sollte jetzt kurz sauber prüfen.",
  "notebook_id": "aa8bda0d-36f1-4993-93c3-9bc0f8837167",
  "artifact_id": "44aafc77-4cf5-46da-b120-7fb75083613b",
  "status": "in_progress",
  "created_at": 1778573999
}